{
    "data": {
        "book_cardio_r": {
            "basic": {
                "can_be_sold": true,
                "categoria": "book_r",
                "description": "Read this book to change your specialisation.\nYou will lose all acquired specialisation points.",
                "name": "Respec Book cardio",
                "quest_item": false,
                "scrap": "none",
                "sprite_ingame": "s_item_book_cardio_r",
                "sprite_inv": "s_item_book_cardio_r",
                "stack_max": 1,
                "value": 10000,
                "weight": 0.5
            }
        },
        "book_charisma_r": {
            "basic": {
                "can_be_sold": true,
                "categoria": "book_r",
                "description": "Read this book to change your specialisation.\nYou will lose all acquired specialisation points.",
                "name": "Respec Book charisma",
                "quest_item": false,
                "scrap": "none",
                "sprite_ingame": "s_item_book_charisma_r",
                "sprite_inv": "s_item_book_charisma_r",
                "stack_max": 1,
                "value": 10000,
                "weight": 0.5
            }
        },
        "book_cooking_r": {
            "basic": {
                "can_be_sold": true,
                "categoria": "book_r",
                "description": "Read this book to change your specialisation.\nYou will lose all acquired specialisation points.",
                "name": "Respec Book cooking",
                "quest_item": false,
                "scrap": "none",
                "sprite_ingame": "s_item_book_cooking_r",
                "sprite_inv": "s_item_book_cooking_r",
                "stack_max": 1,
                "value": 10000,
                "weight": 0.5
            }
        },
        "book_gunsmith_r": {
            "basic": {
                "can_be_sold": true,
                "categoria": "book_r",
                "description": "Read this book to change your specialisation.\nYou will lose all acquired specialisation points.",
                "name": "Respec Book gunsmith",
                "quest_item": false,
                "scrap": "none",
                "sprite_ingame": "s_item_book_gunsmith_r",
                "sprite_inv": "s_item_book_gunsmith_r",
                "stack_max": 1,
                "value": 10000,
                "weight": 0.5
            }
        },
        "book_medicine_r": {
            "basic": {
                "can_be_sold": true,
                "categoria": "book_r",
                "description": "Read this book to change your specialisation.\nYou will lose all acquired specialisation points.",
                "name": "Respec Book medicine",
                "quest_item": false,
                "scrap": "none",
                "sprite_ingame": "s_item_book_medicine_r",
                "sprite_inv": "s_item_book_medicine_r",
                "stack_max": 1,
                "value": 10000,
                "weight": 0.5
            }
        },
        "book_shooting_r": {
            "basic": {
                "can_be_sold": true,
                "categoria": "book_r",
                "description": "Read this book to change your specialisation.\nYou will lose all acquired specialisation points.",
                "name": "Respec Book shooting",
                "quest_item": false,
                "scrap": "none",
                "sprite_ingame": "s_item_book_shooting_r",
                "sprite_inv": "s_item_book_shooting_r",
                "stack_max": 1,
                "value": 10000,
                "weight": 0.5
            }
        },
        "book_style_r": {
            "basic": {
                "can_be_sold": true,
                "categoria": "book_r",
                "description": "Read this book to change your specialisation.\nYou will lose all acquired specialisation points.",
                "name": "Respec Book style",
                "quest_item": false,
                "scrap": "none",
                "sprite_ingame": "s_item_book_style_r",
                "sprite_inv": "s_item_book_style_r",
                "stack_max": 1,
                "value": 10000,
                "weight": 0.5
            }
        }
    },
    "metadata": {
        "author": "Luca",
        "description": "Base gamedata for ZERO Sievert",
        "project": "ZERO Sievert"
    },
    "usage": "item",
    "version": 0
}